krummstab/__init__.py
krummstab/config.py
krummstab/errors.py
krummstab/parsers.py
krummstab/sheets.py
krummstab/strings.py
krummstab/students.py
krummstab/submissions.py
krummstab/teams.py
krummstab/utils.py
krummstab/commands/__init__.py
krummstab/commands/collect.py
krummstab/commands/combine.py
krummstab/commands/init.py
krummstab/commands/mark.py
krummstab/commands/send.py
krummstab/commands/summarize.py
krummstab/schemas/__init__.py
krummstab/schemas/config-schema.json
krummstab/schemas/submission-info-schema.json
krummstab-1.1.1.dist-info/licenses/LICENSE
krummstab-1.1.1.dist-info/METADATA
krummstab-1.1.1.dist-info/WHEEL
krummstab-1.1.1.dist-info/entry_points.txt
krummstab-1.1.1.dist-info/top_level.txt
krummstab-1.1.1.dist-info/RECORD
