Metadata-Version: 2.4
Name: krummstab
Version: 1.1.1
Summary: Efficiently give feedback on ADAM submissions at University of Basel
Home-page: https://github.com/aibasel-teaching/krummstab
Author: Remo Christen
Author-email: remo.christen@unibas.ch
License: GPL3+
Classifier: Environment :: Console
Classifier: Intended Audience :: Education
Classifier: License :: OSI Approved :: GNU General Public License v3 or later (GPLv3+)
Classifier: Programming Language :: Python
Classifier: Programming Language :: Python :: 3.10
Classifier: Topic :: Education
Requires-Python: >=3.10
License-File: LICENSE
Requires-Dist: jsonschema==4.23.0
Requires-Dist: openpyxl==3.1.5
Requires-Dist: pypdf==3.1.0
Dynamic: author
Dynamic: author-email
Dynamic: classifier
Dynamic: description
Dynamic: description-content-type
Dynamic: home-page
Dynamic: license
Dynamic: license-file
Dynamic: requires-dist
Dynamic: requires-python
Dynamic: summary
